rapidenv/__init__.py
rapidenv/__main__.py
rapidenv/console_scripts.py
rapidenv/version.py
rapidenv/__pycache__/__init__.cpython-36.pyc
rapidenv/__pycache__/__init__.cpython-39.pyc
rapidenv/__pycache__/console_scripts.cpython-39.pyc
rapidenv/__pycache__/version.cpython-39.pyc
rapidenv/conan/__init__.py
rapidenv/conan/conan.py
rapidenv/conan/__pycache__/__init__.cpython-36.pyc
rapidenv/conan/__pycache__/__init__.cpython-39.pyc
rapidenv/conan/__pycache__/conan.cpython-36.pyc
rapidenv/conan/__pycache__/conan.cpython-39.pyc
rapidenv/docker/__init__.py
rapidenv/docker/docker.py
rapidenv/docker/__pycache__/__init__.cpython-36.pyc
rapidenv/docker/__pycache__/__init__.cpython-39.pyc
rapidenv/docker/__pycache__/docker.cpython-36.pyc
rapidenv/docker/__pycache__/docker.cpython-39.pyc
rapidenv/git/__init__.py
rapidenv/git/git.py
rapidenv/git/__pycache__/__init__.cpython-36.pyc
rapidenv/git/__pycache__/__init__.cpython-39.pyc
rapidenv/git/__pycache__/git.cpython-36.pyc
rapidenv/git/__pycache__/git.cpython-39.pyc
rapidenv/git/templates/.gitignore
rapidenv/helpers/__init__.py
rapidenv/helpers/validate.py
rapidenv/helpers/__pycache__/__init__.cpython-36.pyc
rapidenv/helpers/__pycache__/__init__.cpython-39.pyc
rapidenv/helpers/__pycache__/validate.cpython-36.pyc
rapidenv/helpers/__pycache__/validate.cpython-39.pyc
rapidenv/osh/__init__.py
rapidenv/osh/copy_large_files.py
rapidenv/osh/download.py
rapidenv/osh/osh.py
rapidenv/osh/__pycache__/__init__.cpython-36.pyc
rapidenv/osh/__pycache__/__init__.cpython-39.pyc
rapidenv/osh/__pycache__/download.cpython-36.pyc
rapidenv/osh/__pycache__/download.cpython-39.pyc
rapidenv/osh/__pycache__/osh.cpython-36.pyc
rapidenv/osh/__pycache__/osh.cpython-39.pyc
rapid_env-0.0.4.dist-info/LICENSE
rapid_env-0.0.4.dist-info/METADATA
rapid_env-0.0.4.dist-info/WHEEL
rapid_env-0.0.4.dist-info/entry_points.txt
rapid_env-0.0.4.dist-info/top_level.txt
rapid_env-0.0.4.dist-info/RECORD
