Metadata-Version: 2.1
Name: rapid-env
Version: 0.0.4
Summary: library with helpers for rapid development environment ramp up, build and distribution.
Home-page: UNKNOWN
License: MIT
Platform: UNKNOWN
Classifier: Programming Language :: Python :: 3
Classifier: License :: OSI Approved :: MIT License
Requires-Python: >=3.6.5
License-File: LICENSE
